{".class": "MypyFile", "_fullname": "pytorch_lightning.trainer.connectors.env_vars_connector", "is_partial_stub_package": false, "is_stub": false, "names": {".class": "SymbolTable", "Callable": {".class": "SymbolTableNode", "cross_ref": "typing.Callable", "kind": "Gdef"}, "__doc__": {".class": "SymbolTableNode", "kind": "Gdef", "node": {".class": "Var", "flags": ["is_ready"], "fullname": "pytorch_lightning.trainer.connectors.env_vars_connector.__doc__", "name": "__doc__", "type": "builtins.str"}}, "__file__": {".class": "SymbolTableNode", "kind": "Gdef", "node": {".class": "Var", "flags": ["is_ready"], "fullname": "pytorch_lightning.trainer.connectors.env_vars_connector.__file__", "name": "__file__", "type": "builtins.str"}}, "__name__": {".class": "SymbolTableNode", "kind": "Gdef", "node": {".class": "Var", "flags": ["is_ready"], "fullname": "pytorch_lightning.trainer.connectors.env_vars_connector.__name__", "name": "__name__", "type": "builtins.str"}}, "__package__": {".class": "SymbolTableNode", "kind": "Gdef", "node": {".class": "Var", "flags": ["is_ready"], "fullname": "pytorch_lightning.trainer.connectors.env_vars_connector.__package__", "name": "__package__", "type": "builtins.str"}}, "get_init_arguments_and_types": {".class": "SymbolTableNode", "cross_ref": "pytorch_lightning.utilities.argparse_utils.get_init_arguments_and_types", "kind": "Gdef"}, "overwrite_by_env_vars": {".class": "SymbolTableNode", "kind": "Gdef", "node": {".class": "FuncDef", "arg_kinds": [0], "arg_names": ["fn"], "flags": [], "fullname": "pytorch_lightning.trainer.connectors.env_vars_connector.overwrite_by_env_vars", "name": "overwrite_by_env_vars", "type": {".class": "CallableType", "arg_kinds": [0], "arg_names": ["fn"], "arg_types": [{".class": "CallableType", "arg_kinds": [2, 4], "arg_names": [null, null], "arg_types": [{".class": "AnyType", "missing_import_name": null, "source_any": null, "type_of_any": 4}, {".class": "AnyType", "missing_import_name": null, "source_any": null, "type_of_any": 4}], "bound_args": [], "def_extras": {}, "fallback": "builtins.function", "implicit": false, "is_ellipsis_args": true, "name": null, "ret_type": {".class": "AnyType", "missing_import_name": null, "source_any": null, "type_of_any": 4}, "variables": []}], "bound_args": [], "def_extras": {"first_arg": null}, "fallback": "builtins.function", "implicit": false, "is_ellipsis_args": false, "name": "overwrite_by_env_vars", "ret_type": {".class": "CallableType", "arg_kinds": [2, 4], "arg_names": [null, null], "arg_types": [{".class": "AnyType", "missing_import_name": null, "source_any": null, "type_of_any": 4}, {".class": "AnyType", "missing_import_name": null, "source_any": null, "type_of_any": 4}], "bound_args": [], "def_extras": {}, "fallback": "builtins.function", "implicit": false, "is_ellipsis_args": true, "name": "__init__ of Trainer", "ret_type": {".class": "AnyType", "missing_import_name": null, "source_any": null, "type_of_any": 4}, "variables": []}, "variables": []}}}, "parse_env_variables": {".class": "SymbolTableNode", "cross_ref": "pytorch_lightning.utilities.argparse_utils.parse_env_variables", "kind": "Gdef"}, "wraps": {".class": "SymbolTableNode", "cross_ref": "functools.wraps", "kind": "Gdef"}}, "path": "/home/ninnart/anaconda3/envs/torch/lib/python3.8/site-packages/pytorch_lightning/trainer/connectors/env_vars_connector.py"}