{".class": "MypyFile", "_fullname": "pytorch_lightning.tuner.tuning", "is_partial_stub_package": false, "is_stub": false, "names": {".class": "SymbolTable", "DataLoader": {".class": "SymbolTableNode", "cross_ref": "torch.utils.data.dataloader.DataLoader", "kind": "Gdef"}, "LightningDataModule": {".class": "SymbolTableNode", "cross_ref": "pytorch_lightning.core.datamodule.LightningDataModule", "kind": "Gdef"}, "LightningModule": {".class": "SymbolTableNode", "cross_ref": "pytorch_lightning.core.lightning.LightningModule", "kind": "Gdef"}, "List": {".class": "SymbolTableNode", "cross_ref": "typing.List", "kind": "Gdef"}, "Optional": {".class": "SymbolTableNode", "cross_ref": "typing.Optional", "kind": "Gdef"}, "Tuner": {".class": "SymbolTableNode", "kind": "Gdef", "node": {".class": "TypeInfo", "_promote": null, "abstract_attributes": [], "bases": ["builtins.object"], "declared_metaclass": null, "defn": {".class": "ClassDef", "fullname": "pytorch_lightning.tuner.tuning.Tuner", "name": "Tuner", "type_vars": []}, "flags": [], "fullname": "pytorch_lightning.tuner.tuning.Tuner", "metaclass_type": null, "metadata": {}, "module_name": "pytorch_lightning.tuner.tuning", "mro": ["pytorch_lightning.tuner.tuning.Tuner", "builtins.object"], "names": {".class": "SymbolTable", "__init__": {".class": "SymbolTableNode", "kind": "Mdef", "node": {".class": "FuncDef", "arg_kinds": [0, 0], "arg_names": ["self", "trainer"], "flags": [], "fullname": "pytorch_lightning.tuner.tuning.Tuner.__init__", "name": "__init__", "type": null}}, "internal_find_lr": {".class": "SymbolTableNode", "kind": "Mdef", "node": {".class": "FuncDef", "arg_kinds": [0, 0, 0], "arg_names": ["self", "trainer", "model"], "flags": [], "fullname": "pytorch_lightning.tuner.tuning.Tuner.internal_find_lr", "name": "internal_find_lr", "type": {".class": "CallableType", "arg_kinds": [0, 0, 0], "arg_names": ["self", "trainer", "model"], "arg_types": ["pytorch_lightning.tuner.tuning.Tuner", {".class": "AnyType", "missing_import_name": null, "source_any": null, "type_of_any": 1}, "pytorch_lightning.core.lightning.LightningModule"], "bound_args": [], "def_extras": {"first_arg": "self"}, "fallback": "builtins.function", "implicit": false, "is_ellipsis_args": false, "name": "internal_find_lr of Tuner", "ret_type": {".class": "AnyType", "missing_import_name": null, "source_any": null, "type_of_any": 1}, "variables": []}}}, "lr_find": {".class": "SymbolTableNode", "kind": "Mdef", "node": {".class": "FuncDef", "arg_kinds": [0, 0, 1, 1, 1, 1, 1, 1, 1, 1], "arg_names": ["self", "model", "train_dataloader", "val_dataloaders", "min_lr", "max_lr", "num_training", "mode", "early_stop_threshold", "datamodule"], "flags": [], "fullname": "pytorch_lightning.tuner.tuning.Tuner.lr_find", "name": "lr_find", "type": {".class": "CallableType", "arg_kinds": [0, 0, 1, 1, 1, 1, 1, 1, 1, 1], "arg_names": ["self", "model", "train_dataloader", "val_dataloaders", "min_lr", "max_lr", "num_training", "mode", "early_stop_threshold", "datamodule"], "arg_types": ["pytorch_lightning.tuner.tuning.Tuner", "pytorch_lightning.core.lightning.LightningModule", {".class": "UnionType", "items": [{".class": "Instance", "args": [{".class": "AnyType", "missing_import_name": null, "source_any": null, "type_of_any": 4}], "type_ref": "torch.utils.data.dataloader.DataLoader"}, {".class": "NoneType"}]}, {".class": "UnionType", "items": [{".class": "Instance", "args": [{".class": "AnyType", "missing_import_name": null, "source_any": null, "type_of_any": 4}], "type_ref": "torch.utils.data.dataloader.DataLoader"}, {".class": "Instance", "args": [{".class": "Instance", "args": [{".class": "AnyType", "missing_import_name": null, "source_any": null, "type_of_any": 4}], "type_ref": "torch.utils.data.dataloader.DataLoader"}], "type_ref": "builtins.list"}, {".class": "NoneType"}]}, "builtins.float", "builtins.float", "builtins.int", "builtins.str", "builtins.float", {".class": "UnionType", "items": ["pytorch_lightning.core.datamodule.LightningDataModule", {".class": "NoneType"}]}], "bound_args": [], "def_extras": {"first_arg": "self"}, "fallback": "builtins.function", "implicit": false, "is_ellipsis_args": false, "name": "lr_find of Tuner", "ret_type": {".class": "AnyType", "missing_import_name": null, "source_any": null, "type_of_any": 1}, "variables": []}}}, "on_trainer_init": {".class": "SymbolTableNode", "kind": "Mdef", "node": {".class": "FuncDef", "arg_kinds": [0, 0, 0], "arg_names": ["self", "auto_lr_find", "auto_scale_batch_size"], "flags": [], "fullname": "pytorch_lightning.tuner.tuning.Tuner.on_trainer_init", "name": "on_trainer_init", "type": null}}, "pick_multiple_gpus": {".class": "SymbolTableNode", "kind": "Mdef", "node": {".class": "FuncDef", "arg_kinds": [0, 0], "arg_names": ["self", "num_gpus"], "flags": [], "fullname": "pytorch_lightning.tuner.tuning.Tuner.pick_multiple_gpus", "name": "pick_multiple_gpus", "type": {".class": "CallableType", "arg_kinds": [0, 0], "arg_names": ["self", "num_gpus"], "arg_types": ["pytorch_lightning.tuner.tuning.Tuner", "builtins.int"], "bound_args": [], "def_extras": {"first_arg": "self"}, "fallback": "builtins.function", "implicit": false, "is_ellipsis_args": false, "name": "pick_multiple_gpus of Tuner", "ret_type": {".class": "AnyType", "missing_import_name": null, "source_any": null, "type_of_any": 1}, "variables": []}}}, "scale_batch_size": {".class": "SymbolTableNode", "kind": "Mdef", "node": {".class": "FuncDef", "arg_kinds": [0, 0, 1, 1, 1, 1, 1, 4], "arg_names": ["self", "model", "mode", "steps_per_trial", "init_val", "max_trials", "batch_arg_name", "fit_kwargs"], "flags": [], "fullname": "pytorch_lightning.tuner.tuning.Tuner.scale_batch_size", "name": "scale_batch_size", "type": {".class": "CallableType", "arg_kinds": [0, 0, 1, 1, 1, 1, 1, 4], "arg_names": ["self", "model", "mode", "steps_per_trial", "init_val", "max_trials", "batch_arg_name", "fit_kwargs"], "arg_types": ["pytorch_lightning.tuner.tuning.Tuner", {".class": "AnyType", "missing_import_name": null, "source_any": null, "type_of_any": 1}, "builtins.str", "builtins.int", "builtins.int", "builtins.int", "builtins.str", {".class": "AnyType", "missing_import_name": null, "source_any": null, "type_of_any": 1}], "bound_args": [], "def_extras": {"first_arg": "self"}, "fallback": "builtins.function", "implicit": false, "is_ellipsis_args": false, "name": "scale_batch_size of Tuner", "ret_type": {".class": "AnyType", "missing_import_name": null, "source_any": null, "type_of_any": 1}, "variables": []}}}, "trainer": {".class": "SymbolTableNode", "implicit": true, "kind": "Mdef", "node": {".class": "Var", "flags": [], "fullname": "pytorch_lightning.tuner.tuning.Tuner.trainer", "name": "trainer", "type": {".class": "AnyType", "missing_import_name": null, "source_any": null, "type_of_any": 1}}}, "tune": {".class": "SymbolTableNode", "kind": "Mdef", "node": {".class": "FuncDef", "arg_kinds": [0, 0, 0, 0, 0], "arg_names": ["self", "model", "train_dataloader", "val_dataloaders", "datamodule"], "flags": [], "fullname": "pytorch_lightning.tuner.tuning.Tuner.tune", "name": "tune", "type": null}}}, "tuple_type": null, "type_vars": [], "typeddict_type": null}}, "Union": {".class": "SymbolTableNode", "cross_ref": "typing.Union", "kind": "Gdef"}, "__doc__": {".class": "SymbolTableNode", "kind": "Gdef", "node": {".class": "Var", "flags": ["is_ready"], "fullname": "pytorch_lightning.tuner.tuning.__doc__", "name": "__doc__", "type": "builtins.str"}}, "__file__": {".class": "SymbolTableNode", "kind": "Gdef", "node": {".class": "Var", "flags": ["is_ready"], "fullname": "pytorch_lightning.tuner.tuning.__file__", "name": "__file__", "type": "builtins.str"}}, "__name__": {".class": "SymbolTableNode", "kind": "Gdef", "node": {".class": "Var", "flags": ["is_ready"], "fullname": "pytorch_lightning.tuner.tuning.__name__", "name": "__name__", "type": "builtins.str"}}, "__package__": {".class": "SymbolTableNode", "kind": "Gdef", "node": {".class": "Var", "flags": ["is_ready"], "fullname": "pytorch_lightning.tuner.tuning.__package__", "name": "__package__", "type": "builtins.str"}}, "_run_lr_finder_internally": {".class": "SymbolTableNode", "cross_ref": "pytorch_lightning.tuner.lr_finder._run_lr_finder_internally", "kind": "Gdef"}, "lr_find": {".class": "SymbolTableNode", "cross_ref": "pytorch_lightning.tuner.lr_finder.lr_find", "kind": "Gdef"}, "pick_multiple_gpus": {".class": "SymbolTableNode", "cross_ref": "pytorch_lightning.tuner.auto_gpu_select.pick_multiple_gpus", "kind": "Gdef"}, "scale_batch_size": {".class": "SymbolTableNode", "cross_ref": "pytorch_lightning.tuner.batch_size_scaling.scale_batch_size", "kind": "Gdef"}}, "path": "/home/ninnart/anaconda3/envs/torch/lib/python3.8/site-packages/pytorch_lightning/tuner/tuning.py"}